gda_analysis/compare_to_manifest/__init__.py
gda_analysis/compare_to_manifest/compare_to_manifest.py
gda_analysis/convert_gs_to_df/__init__.py
gda_analysis/convert_gs_to_df/convert_gs_to_df.py
gda_analysis/convert_vcf_to_df/__init__.py
gda_analysis/convert_vcf_to_df/convert_vcf_to_df.py
gda_analysis/create_dfs.py
gda_analysis/dal/__init__.py
gda_analysis/dal/connect_db.py
gda_analysis/display_dataset.py
gda_analysis/save_dfs_as_csv.py
gda_analysis/validation_tests/__init__.py
gda_analysis/validation_tests/validation_tests.py
gda_analysis-0.1.7.dist-info/entry_points.txt
gda_analysis-0.1.7.dist-info/WHEEL
gda_analysis-0.1.7.dist-info/METADATA
gda_analysis-0.1.7.dist-info/RECORD
